gbn/__init__.py
gbn/cli.py
gbn/ocrd-tool.json
gbn/tool.py
gbn/lib/__init__.py
gbn/lib/dl.py
gbn/lib/struct.py
gbn/lib/util.py
gbn/sbb/__init__.py
gbn/sbb/binarize.py
gbn/sbb/crop.py
gbn/sbb/predict.py
gbn/sbb/segment.py
ocrd_gbn-1.0.0.dist-info/LICENSE
ocrd_gbn-1.0.0.dist-info/METADATA
ocrd_gbn-1.0.0.dist-info/WHEEL
ocrd_gbn-1.0.0.dist-info/entry_points.txt
ocrd_gbn-1.0.0.dist-info/top_level.txt
ocrd_gbn-1.0.0.dist-info/RECORD
