Metadata-Version: 2.1
Name: ocrd-gbn
Version: 1.0.0
Summary: Collection of OCR-D compliant tools for layout analysis and segmentation of historical german-language documents published in Brazil
Home-page: https://github.com/sulzbals/gbn
Author: Lucas Sulzbach
Author-email: lucas@sulzbach.org
License: Apache
Keywords: OCR,OCR-D
Platform: UNKNOWN
Classifier: Intended Audience :: Science/Research
Classifier: License :: OSI Approved :: Apache Software License
Classifier: Programming Language :: Python :: 3
Classifier: Topic :: Scientific/Engineering :: Artificial Intelligence
Requires-Python: >=3.6.0
Requires-Dist: opencv-python-headless
Requires-Dist: matplotlib
Requires-Dist: seaborn
Requires-Dist: tqdm
Requires-Dist: keras (==2.3.*)
Requires-Dist: shapely
Requires-Dist: scikit-learn
Requires-Dist: tensorflow-gpu (~=1.15.2)
Requires-Dist: scipy
Requires-Dist: ocrd (>=2.0.0)
